duvida/__init__.py
duvida/config.py
duvida/hessians.py
duvida/hvp.py
duvida/information.py
duvida/types.py
duvida/utils.py
duvida/numpy/__init__.py
duvida/numpy/numpy.py
duvida-0.0.3.post1.dist-info/LICENSE
duvida-0.0.3.post1.dist-info/METADATA
duvida-0.0.3.post1.dist-info/WHEEL
duvida-0.0.3.post1.dist-info/top_level.txt
duvida-0.0.3.post1.dist-info/RECORD
