Metadata-Version: 2.1
Name: duvida
Version: 0.0.3.post1
Summary: Calculating exact and approximate confidence and information metrics for differentiable functions.
Author-email: Eachan Johnson <eachan.johnson@crick.ac.uk>
License: MIT License
Project-URL: Homepage, https://github.com/scbirlab/duvida
Project-URL: Bug Tracker, https://github.com/scbirlab/duvida/issues
Keywords: ai,active-learning,bayesian-optimization,data,deep-learning,machine-learning
Classifier: Development Status :: 3 - Alpha
Classifier: Intended Audience :: Science/Research
Classifier: Topic :: Scientific/Engineering :: Artificial Intelligence
Classifier: License :: OSI Approved :: MIT License
Classifier: Programming Language :: Python :: 3.10
Classifier: Programming Language :: Python :: 3.11
Classifier: Programming Language :: Python :: 3.12
Classifier: Programming Language :: Python :: 3.13
Classifier: Programming Language :: Python :: 3 :: Only
Requires-Python: >=3.10
License-File: LICENSE
Requires-Dist: carabiner-tools[mpl,pd]>=0.0.4
Requires-Dist: numpy
Requires-Dist: tqdm
Provides-Extra: jax
Requires-Dist: jax>=0.5.3; extra == "jax"
Provides-Extra: jax_cuda12
Requires-Dist: jax[cuda12]>=0.5.3; extra == "jax-cuda12"
Provides-Extra: jax_cuda12_local
Requires-Dist: jax[cuda12_local]>=0.5.3; extra == "jax-cuda12-local"
Provides-Extra: torch
Requires-Dist: torch>=2.4; extra == "torch"
Requires-Dist: torchvision; extra == "torch"
Requires-Dist: lightning; extra == "torch"
Requires-Dist: tensorboard; extra == "torch"
